another_linked_list/__init__.py
another_linked_list/_vendor/__init__.py
another_linked_list/_vendor/all_purpose_set/__init__.py
another_linked_list/_vendor/all_purpose_set/_vendor/__init__.py
another_linked_list/_vendor/all_purpose_set/_vendor/ordered_set-3.1.1-py3.7.egg-info/PKG-INFO
another_linked_list/_vendor/all_purpose_set/_vendor/ordered_set-3.1.1-py3.7.egg-info/SOURCES.txt
another_linked_list/_vendor/all_purpose_set/_vendor/ordered_set-3.1.1-py3.7.egg-info/dependency_links.txt
another_linked_list/_vendor/all_purpose_set/_vendor/ordered_set-3.1.1-py3.7.egg-info/installed-files.txt
another_linked_list/_vendor/all_purpose_set/_vendor/ordered_set-3.1.1-py3.7.egg-info/top_level.txt
another_linked_list/_vendor/all_purpose_set/_vendor/ordered_set.py
another_linked_list/_vendor/all_purpose_set/_vendor/tedent/__init__.py
another_linked_list/_vendor/all_purpose_set/_vendor/tedent/_vendor/__init__.py
another_linked_list/_vendor/all_purpose_set/_vendor/tedent/_vendor/ordered_set-3.1.1-py3.7.egg-info/PKG-INFO
another_linked_list/_vendor/all_purpose_set/_vendor/tedent/_vendor/ordered_set-3.1.1-py3.7.egg-info/SOURCES.txt
another_linked_list/_vendor/all_purpose_set/_vendor/tedent/_vendor/ordered_set-3.1.1-py3.7.egg-info/dependency_links.txt
another_linked_list/_vendor/all_purpose_set/_vendor/tedent/_vendor/ordered_set-3.1.1-py3.7.egg-info/installed-files.txt
another_linked_list/_vendor/all_purpose_set/_vendor/tedent/_vendor/ordered_set-3.1.1-py3.7.egg-info/top_level.txt
another_linked_list/_vendor/all_purpose_set/_vendor/tedent/_vendor/ordered_set.py
another_linked_list/_vendor/all_purpose_set/_vendor/tedent/_vendor/wrapt/__init__.py
another_linked_list/_vendor/all_purpose_set/_vendor/tedent/_vendor/wrapt/_wrappers.cpython-37m-x86_64-linux-gnu.so
another_linked_list/_vendor/all_purpose_set/_vendor/tedent/_vendor/wrapt/decorators.py
another_linked_list/_vendor/all_purpose_set/_vendor/tedent/_vendor/wrapt/importer.py
another_linked_list/_vendor/all_purpose_set/_vendor/tedent/_vendor/wrapt/wrappers.py
another_linked_list/_vendor/all_purpose_set/_vendor/tedent/_vendor/wrapt-1.11.1.dist-info/INSTALLER
another_linked_list/_vendor/all_purpose_set/_vendor/tedent/_vendor/wrapt-1.11.1.dist-info/LICENSE
another_linked_list/_vendor/all_purpose_set/_vendor/tedent/_vendor/wrapt-1.11.1.dist-info/METADATA
another_linked_list/_vendor/all_purpose_set/_vendor/tedent/_vendor/wrapt-1.11.1.dist-info/RECORD
another_linked_list/_vendor/all_purpose_set/_vendor/tedent/_vendor/wrapt-1.11.1.dist-info/WHEEL
another_linked_list/_vendor/all_purpose_set/_vendor/tedent/_vendor/wrapt-1.11.1.dist-info/top_level.txt
another_linked_list/_vendor/all_purpose_set/_vendor/tedent/fns/__init__.py
another_linked_list/_vendor/all_purpose_set/_vendor/tedent/fns/all_.py
another_linked_list/_vendor/all_purpose_set/_vendor/tedent/fns/decorators/__init__.py
another_linked_list/_vendor/all_purpose_set/_vendor/tedent/fns/decorators/argIsCallable.py
another_linked_list/_vendor/all_purpose_set/_vendor/tedent/fns/decorators/argIsClass.py
another_linked_list/_vendor/all_purpose_set/_vendor/tedent/fns/decorators/argIsListOfType.py
another_linked_list/_vendor/all_purpose_set/_vendor/tedent/fns/decorators/argIsType.py
another_linked_list/_vendor/all_purpose_set/_vendor/tedent/fns/discardFirst.py
another_linked_list/_vendor/all_purpose_set/_vendor/tedent/fns/discardLastWhile.py
another_linked_list/_vendor/all_purpose_set/_vendor/tedent/fns/forEach.py
another_linked_list/_vendor/all_purpose_set/_vendor/tedent/fns/iif.py
another_linked_list/_vendor/all_purpose_set/_vendor/tedent/fns/internal/__init__.py
another_linked_list/_vendor/all_purpose_set/_vendor/tedent-0.1.5.dist-info/INSTALLER
another_linked_list/_vendor/all_purpose_set/_vendor/tedent-0.1.5.dist-info/METADATA
another_linked_list/_vendor/all_purpose_set/_vendor/tedent-0.1.5.dist-info/RECORD
another_linked_list/_vendor/all_purpose_set/_vendor/tedent-0.1.5.dist-info/WHEEL
another_linked_list/_vendor/all_purpose_set/_vendor/tedent-0.1.5.dist-info/top_level.txt
another_linked_list/_vendor/all_purpose_set/_vendor/wrapt-1.10.11.dist-info/INSTALLER
another_linked_list/_vendor/all_purpose_set/_vendor/wrapt-1.10.11.dist-info/LICENSE
another_linked_list/_vendor/all_purpose_set/_vendor/wrapt-1.10.11.dist-info/METADATA
another_linked_list/_vendor/all_purpose_set/_vendor/wrapt-1.10.11.dist-info/RECORD
another_linked_list/_vendor/all_purpose_set/_vendor/wrapt-1.10.11.dist-info/WHEEL
another_linked_list/_vendor/all_purpose_set/_vendor/wrapt-1.10.11.dist-info/top_level.txt
another_linked_list/_vendor/all_purpose_set-0.1.10.dist-info/INSTALLER
another_linked_list/_vendor/all_purpose_set-0.1.10.dist-info/METADATA
another_linked_list/_vendor/all_purpose_set-0.1.10.dist-info/RECORD
another_linked_list/_vendor/all_purpose_set-0.1.10.dist-info/WHEEL
another_linked_list/_vendor/all_purpose_set-0.1.10.dist-info/top_level.txt
another_linked_list/_vendor/ordered_set-3.1.1-py3.7.egg-info/PKG-INFO
another_linked_list/_vendor/ordered_set-3.1.1-py3.7.egg-info/SOURCES.txt
another_linked_list/_vendor/ordered_set-3.1.1-py3.7.egg-info/dependency_links.txt
another_linked_list/_vendor/ordered_set-3.1.1-py3.7.egg-info/installed-files.txt
another_linked_list/_vendor/ordered_set-3.1.1-py3.7.egg-info/top_level.txt
another_linked_list/_vendor/tedent/_vendor/ordered_set-3.1.1-py3.7.egg-info/PKG-INFO
another_linked_list/_vendor/tedent/_vendor/ordered_set-3.1.1-py3.7.egg-info/SOURCES.txt
another_linked_list/_vendor/tedent/_vendor/ordered_set-3.1.1-py3.7.egg-info/dependency_links.txt
another_linked_list/_vendor/tedent/_vendor/ordered_set-3.1.1-py3.7.egg-info/installed-files.txt
another_linked_list/_vendor/tedent/_vendor/ordered_set-3.1.1-py3.7.egg-info/top_level.txt
another_linked_list/_vendor/tedent/_vendor/wrapt-1.11.1.dist-info/INSTALLER
another_linked_list/_vendor/tedent/_vendor/wrapt-1.11.1.dist-info/LICENSE
another_linked_list/_vendor/tedent/_vendor/wrapt-1.11.1.dist-info/METADATA
